{
  "payload": {
    "gatherer": [
      {
        "id": 1,
        "type": "GATHERER",
        "subType": "MINING_SHIP",
        "name": "Miner ship",
        "desc": "Mine minerals from asteroids",
        "cost": {
          "titanium": 10,
          "energy": 20
        },
        "time": 10
      },
      {
        "id": 2,
        "type": "GATHERER",
        "subType": "NEBULA_GATHER_SHIP",
        "name": "Helios",
        "desc": "Produce crews for ships...etc..TBD",
        "cost": {
          "titanium": 10,
          "energy": 20
        },
        "time": 10
      }
    ],
    "military": [
      {
        "id": 1,
        "type": "MILITARY",
        "subType": "CAPITAL_SHIP",
        "name": "Thor",
        "desc": "Bid mothafuka capital ship",
        "cost": {
          "titanium": 10,
          "energy": 20
        },
        "time": 10
      }
    ],
    "defensive": [
      {
        "id": 1,
        "type": "DEFENSIVE",
        "subType": "PHALANX",
        "name": "Phalanx",
        "desc": "Strong defensive space ship, protect allies",
        "cost": {
          "titanium": 10,
          "energy": 20
        },
        "time": 10
      }
    ],
    "pioneer": [
      {
        "id": 1,
        "type": "PIONEER",
        "subType": "SCOUT",
        "name": "Voyager",
        "desc": "Scout the unknown...",
        "cost": {
          "titanium": 10,
          "energy": 20
        },
        "time": 10
      }
    ]
  },
  "type": "OK"
}